<?xml version='1.0' encoding='UTF-8'?>
<SupplierProductFeed xmlns="http://walmart.com/suppliers/">
	<version>1.4.1</version>
	<SupplierProduct>
		<productName>Just My Style®Designer Hair Wear Kit by Horizon Group USA</productName>
		<longDescription>6 Satin Headbands
4 Hair Ties
50 Sparkling Gemstones
1 Fabric Glue Net Wt 0.023 Fl oz (6ml)
8 Colorful Feathers
3 Ribbon Bows
2 Flower Embellishments
5 Felt Circles
Easy-to-Follow Instructions</longDescription>
		<shortDescription>The Just My Style® Designer Hair Wear comes with everything you need to create 10 creations for your hair! The kit comes with satin headbands, hair ties, sparkling gemstones, fabric glue, colorful feathers, ribbon bows, flower embellishments and felt circles.</shortDescription>
		<mainImage>
			<mainImageUrl>https://albert-test.contentanalyticsinc.com/temp/2016012746237F.jpg</mainImageUrl>
		</mainImage>
		<additionalAssets>
			<additionalAsset>
				<assetUrl>https://albert-test.contentanalyticsinc.com/temp/20160127EAAFEE.jpg</assetUrl>
				<assetType>Additional Image</assetType>
			</additionalAsset>
			<additionalAsset>
				<assetUrl>https://albert-test.contentanalyticsinc.com/temp/20160127AC9FE9.jpg</assetUrl>
				<assetType>Additional Image</assetType>
			</additionalAsset>
			<additionalAsset>
				<assetUrl>https://albert-test.contentanalyticsinc.com/temp/20160127F4170F.jpg</assetUrl>
				<assetType>Additional Image</assetType>
			</additionalAsset>
		</additionalAssets>
		<productIdentifiers>
			<productIdentifier>
				<productIdType>UPC</productIdType>
				<productId>765940578834</productId>
			</productIdentifier>
		</productIdentifiers>
		<unitsPerConsumerUnit>1</unitsPerConsumerUnit>
		<countryOfOriginAssembly>CN</countryOfOriginAssembly>
		<countryOfOriginComponents>Imported</countryOfOriginComponents>
		<isAerosol>false</isAerosol>
		<isChemical>true</isChemical>
		<isPesticide>false</isPesticide>
		<hasBatteries>false</hasBatteries>
		<containsMercury>false</containsMercury>
		<hasFuelContainer>false</hasFuelContainer>
		<pricePerUnitQuantity>
			<unit>Kilogram</unit>
			<measure>1</measure>
		</pricePerUnitQuantity>
		<containsPaperWood>false</containsPaperWood>
		<compositeWoodCertificationCode>1</compositeWoodCertificationCode>
		<hasExpiration>false</hasExpiration>
		<hasWarnings>false</hasWarnings>
		<hasWarranty>false</hasWarranty>
		<isProp65WarningRequired>false</isProp65WarningRequired>
		<isTemperatureSensitive>false</isTemperatureSensitive>
		<smallPartsWarnings>
			<smallPartsWarning>0</smallPartsWarning>
		</smallPartsWarnings>
		<isControlledSubstance>false</isControlledSubstance>
		<hasStateRestrictions>false</hasStateRestrictions>
		<ArtAndCraft>
			<isRefillable>false</isRefillable>
			<isRecyclable>false</isRecyclable>
			<brand>Just My Style</brand>
			<factoryId>36113895</factoryId>
			<gender>Unisex</gender>
		</ArtAndCraft>
	</SupplierProduct>
</SupplierProductFeed>
